evolverx/__init__.py
evolverx/evolving.py
evolverx/llm.py
evolverx/persist.py
evolverx/py.typed
evolverx/sandbox.py
evolverx/telemetry.py
evolverx/types.py
evolverx-0.1.2.dist-info/licenses/LICENSE
evolverx-0.1.2.dist-info/licenses/NOTICE
evolverx-0.1.2.dist-info/METADATA
evolverx-0.1.2.dist-info/WHEEL
evolverx-0.1.2.dist-info/entry_points.txt
evolverx-0.1.2.dist-info/top_level.txt
evolverx-0.1.2.dist-info/RECORD
