Metadata-Version: 2.4
Name: evolverx
Version: 0.1.2
Summary: Self‑evolving decorator: fall back to LLM on failure, then persist clean Python for the happy path.
Author-email: Vladimir Ponomarev <vorba.dev@gmail.com>
License: Apache-2.0
Project-URL: Homepage, https://github.com/vorba-vp/evolverx
Project-URL: Repository, https://github.com/vorba-vp/evolverx
Project-URL: Issues, https://github.com/vorba-vp/evolverx/issues
Project-URL: Documentation, https://github.com/vorba-vp/evolverx#readme
Classifier: Development Status :: 3 - Alpha
Classifier: Intended Audience :: Developers
Classifier: License :: OSI Approved :: Apache Software License
Classifier: Programming Language :: Python :: 3
Classifier: Programming Language :: Python :: 3.10
Classifier: Programming Language :: Python :: 3.11
Classifier: Programming Language :: Python :: 3.12
Classifier: Topic :: Software Development :: Libraries
Requires-Python: >=3.10
License-File: LICENSE
License-File: NOTICE
Requires-Dist: typing-extensions>=4.9.0
Requires-Dist: openai<2.0,>=1.40
Dynamic: license-file
